[
  { "company": "Coinbase",           "tokens": ["coinbase"] },
  { "company": "Zendesk",            "tokens": ["zendesk"] },
  { "company": "Chime",              "tokens": ["chime"] },
  { "company": "Squarespace",        "tokens": ["squarespace"] },
  { "company": "1Password",          "tokens": ["1password", "onepassword", "agilebits"] },
  { "company": "Zapier",             "tokens": ["zapier"] },
  { "company": "Benchling",          "tokens": ["benchling"] },
  { "company": "Checkr",             "tokens": ["checkr"] },
  { "company": "Faire",              "tokens": ["faire", "faire-wholesale"] },
  { "company": "Procore",            "tokens": ["procore"] },
  { "company": "Lattice",            "tokens": ["lattice"] },
  { "company": "Sourcegraph",        "tokens": ["sourcegraph"] },
  { "company": "Loom",               "tokens": ["loom", "loomsystems"] },
  { "company": "Mercury",            "tokens": ["mercury", "mercurytechnologies"] },
  { "company": "Navan",              "tokens": ["navan", "tripactions"] },
  { "company": "Retool",             "tokens": ["retool"] },
  { "company": "Samsara",            "tokens": ["samsara"] },
  { "company": "Wealthsimple",       "tokens": ["wealthsimple", "wealthsimplecanada"] },
  { "company": "Carta",              "tokens": ["carta", "eshares"] },
  { "company": "Chili Piper",        "tokens": ["chilipiper"] },
  { "company": "Clari",              "tokens": ["clari"] },
  { "company": "Cockroach Labs",     "tokens": ["cockroachlabs"] },
  { "company": "Gong",               "tokens": ["gong"] },
  { "company": "Harness",            "tokens": ["harness"] },
  { "company": "Honeycomb",          "tokens": ["honeycomb", "honeycombio"] },
  { "company": "Ironclad",           "tokens": ["ironclad"] },
  { "company": "Lacework",           "tokens": ["lacework"] },
  { "company": "Mapbox",             "tokens": ["mapbox"] },
  { "company": "Nextdoor",           "tokens": ["nextdoor"] },
  { "company": "Noom",               "tokens": ["noom"] },
  { "company": "Outreach",           "tokens": ["outreach"] },
  { "company": "Persona",            "tokens": ["persona", "withpersona"] },
  { "company": "Poshmark",           "tokens": ["poshmark"] },
  { "company": "Productboard",       "tokens": ["productboard"] },
  { "company": "Salesloft",          "tokens": ["salesloft"] },
  { "company": "SentinelOne",        "tokens": ["sentinelone"] },
  { "company": "Snyk",               "tokens": ["snyk"] },
  { "company": "Socure",             "tokens": ["socure"] },
  { "company": "Stytch",             "tokens": ["stytch"] },
  { "company": "Superhuman",         "tokens": ["superhuman"] },
  { "company": "Vectra AI",          "tokens": ["vectraai", "vectra"] },
  { "company": "WalkMe",             "tokens": ["walkme"] },
  { "company": "Weights & Biases",   "tokens": ["wandb", "weightsbiases"] },
  { "company": "Wiz",                "tokens": ["wiz"] },
  { "company": "Abnormal Security",  "tokens": ["abnormalsecurity", "abnormal"] },
  { "company": "Algolia",            "tokens": ["algolia"] },
  { "company": "Appsflyer",          "tokens": ["appsflyer"] },
  { "company": "Auth0",              "tokens": ["auth0"] },
  { "company": "Betterment",         "tokens": ["betterment"] },
  { "company": "BigCommerce",        "tokens": ["bigcommerce"] },
  { "company": "Bloomreach",         "tokens": ["bloomreach"] },
  { "company": "Branch",             "tokens": ["branch", "branchmetrics"] },
  { "company": "Braze",              "tokens": ["braze"] },
  { "company": "Calm",               "tokens": ["calm"] },
  { "company": "Celonis",            "tokens": ["celonis"] },
  { "company": "CircleCI",           "tokens": ["circleci"] },
  { "company": "Clearbit",           "tokens": ["clearbit"] },
  { "company": "ClickHouse",         "tokens": ["clickhouse"] },
  { "company": "Coralogix",          "tokens": ["coralogix"] },
  { "company": "DataStax",           "tokens": ["datastax"] },
  { "company": "Domo",               "tokens": ["domo"] },
  { "company": "Drift",              "tokens": ["drift"] },
  { "company": "Etsy",               "tokens": ["etsy"] },
  { "company": "Eventbrite",         "tokens": ["eventbrite"] },
  { "company": "Expensify",          "tokens": ["expensify"] },
  { "company": "Front",              "tokens": ["front", "frontapp"] },
  { "company": "GitHub",             "tokens": ["github"] },
  { "company": "GoodRx",             "tokens": ["goodrx"] },
  { "company": "Grafana Labs",       "tokens": ["grafana"] },
  { "company": "Headspace",          "tokens": ["headspace"] },
  { "company": "Hex",                "tokens": ["hex", "hex-inc"] },
  { "company": "Hinge Health",       "tokens": ["hingehealth"] },
  { "company": "Human Interest",     "tokens": ["humaninterest"] },
  { "company": "Huntress",           "tokens": ["huntress"] },
  { "company": "InfluxData",         "tokens": ["influxdata"] },
  { "company": "Iterable",           "tokens": ["iterable"] },
  { "company": "Justworks",          "tokens": ["justworks"] },
  { "company": "Klaviyo",            "tokens": ["klaviyo"] },
  { "company": "Lime",               "tokens": ["lime", "limebike"] },
  { "company": "LogRocket",          "tokens": ["logrocket"] },
  { "company": "Marqeta",            "tokens": ["marqeta"] },
  { "company": "Navan",              "tokens": ["navan", "tripactions"] },
  { "company": "Nexthink",           "tokens": ["nexthink"] },
  { "company": "Opendoor",           "tokens": ["opendoor"] },
  { "company": "OpenSea",            "tokens": ["opensea"] },
  { "company": "PandaDoc",           "tokens": ["pandadoc"] },
  { "company": "Podium",             "tokens": ["podium"] },
  { "company": "Prefect",            "tokens": ["prefect"] },
  { "company": "Recharge",           "tokens": ["recharge", "rechargeapps"] },
  { "company": "Ro",                 "tokens": ["ro", "romanhealth"] },
  { "company": "Sauce Labs",         "tokens": ["saucelabs"] },
  { "company": "Shopify",            "tokens": ["shopify"] },
  { "company": "Signifyd",           "tokens": ["signifyd"] },
  { "company": "Skydio",             "tokens": ["skydio"] },
  { "company": "Sonatype",           "tokens": ["sonatype"] },
  { "company": "Sprout Social",      "tokens": ["sproutsocial"] },
  { "company": "Statsig",            "tokens": ["statsig"] },
  { "company": "Sumo Logic",         "tokens": ["sumologic"] },
  { "company": "Sword Health",       "tokens": ["swordhealth"] },
  { "company": "Tailscale",          "tokens": ["tailscale"] },
  { "company": "Temporal",           "tokens": ["temporal", "temporalio"] },
  { "company": "TripAdvisor",        "tokens": ["tripadvisor"] },
  { "company": "Udemy",              "tokens": ["udemy"] },
  { "company": "UserTesting",        "tokens": ["usertesting"] },
  { "company": "Verkada",            "tokens": ["verkada"] },
  { "company": "Watershed",          "tokens": ["watershed"] },
  { "company": "Whatfix",            "tokens": ["whatfix"] },
  { "company": "Writer",             "tokens": ["writer"] },
  { "company": "Xero",               "tokens": ["xero"] },
  { "company": "Yotpo",              "tokens": ["yotpo"] },
  { "company": "ZoomInfo",           "tokens": ["zoominfo"] },
  { "company": "Zuora",              "tokens": ["zuora"] },
  { "company": "Harness",            "tokens": ["harness"] },
  { "company": "Weights & Biases",   "tokens": ["wandb"] },
  { "company": "Productboard",       "tokens": ["productboard"] },
  { "company": "Sentry",             "tokens": ["sentry"] },
  { "company": "LaunchDarkly",       "tokens": ["launchdarkly"] },
  { "company": "Split.io",           "tokens": ["split", "splitio"] },
  { "company": "Statsig",            "tokens": ["statsig"] },
  { "company": "Optimizely",         "tokens": ["optimizely"] },
  { "company": "Taboola",            "tokens": ["taboola"] },
  { "company": "Outbrain",           "tokens": ["outbrain"] },
  { "company": "AppsFlyer",          "tokens": ["appsflyer"] },
  { "company": "Adjust",             "tokens": ["adjust"] },
  { "company": "Amplitude",          "tokens": ["amplitude"] },
  { "company": "Heap",               "tokens": ["heap"] },
  { "company": "FullStory",          "tokens": ["fullstory"] },
  { "company": "Hotjar",             "tokens": ["hotjar"] },
  { "company": "Crazy Egg",          "tokens": ["crazyegg"] },
  { "company": "Segment",            "tokens": ["segment"] },
  { "company": "Rudderstack",        "tokens": ["rudderstack"] },
  { "company": "Jitsu",              "tokens": ["jitsu"] },
  { "company": "Stape",              "tokens": ["stape"] },
  { "company": "Airbyte",            "tokens": ["airbyte"] },
  { "company": "Hightouch",          "tokens": ["hightouch"] },
  { "company": "Census",             "tokens": ["census", "getcensus"] },
  { "company": "Fivetran",           "tokens": ["fivetran"] },
  { "company": "Stitch",             "tokens": ["stitch", "stitchdata"] },
  { "company": "Matillion",          "tokens": ["matillion"] },
  { "company": "dbt Labs",           "tokens": ["dbtlabs", "dbt-labs"] },
  { "company": "Monte Carlo",        "tokens": ["montecarlodata", "montecarlo"] },
  { "company": "Lightdash",          "tokens": ["lightdash"] },
  { "company": "Metabase",           "tokens": ["metabase"] },
  { "company": "Retool",             "tokens": ["retool"] },
  { "company": "Appsmith",           "tokens": ["appsmith"] },
  { "company": "Budibase",           "tokens": ["budibase"] },
  { "company": "NocoDB",             "tokens": ["nocodb"] },
  { "company": "Baserow",            "tokens": ["baserow"] },
  { "company": "Airtable",           "tokens": ["airtable"] },
  { "company": "Notion",             "tokens": ["notion"] },
  { "company": "Coda",               "tokens": ["coda", "codahq"] },
  { "company": "DigitalOcean",       "tokens": ["digitalocean"] },
  { "company": "Mux",                "tokens": ["mux", "mux-inc"] },
  { "company": "Doppler",            "tokens": ["doppler"] },
  { "company": "Incident.io",        "tokens": ["incident-io", "incidentio"] },
  { "company": "Clerk",              "tokens": ["clerk", "clerkdev"] },
  { "company": "Stedi",              "tokens": ["stedi"] },
  { "company": "Courier",            "tokens": ["courier", "trycourier"] },
  { "company": "Cal.com",            "tokens": ["cal-com", "calcom"] },
  { "company": "Trigger.dev",        "tokens": ["trigger-dev", "triggerdev"] },
  { "company": "Neon",               "tokens": ["neon", "neondatabase"] },
  { "company": "Inngest",            "tokens": ["inngest"] },
  { "company": "Mintlify",           "tokens": ["mintlify"] },
  { "company": "Novu",               "tokens": ["novu"] },
  { "company": "Unkey",              "tokens": ["unkey"] },
  { "company": "Turso",              "tokens": ["turso", "chiselstrike"] },
  { "company": "Better Stack",       "tokens": ["betterstack", "logtail"] },
  { "company": "Dub",                "tokens": ["dub", "dubco"] },
  { "company": "Infisical",          "tokens": ["infisical"] },
  { "company": "Permit.io",          "tokens": ["permit", "permit-io"] },
  { "company": "Graphite",           "tokens": ["graphite", "graphitehq"] },
  { "company": "Warp",               "tokens": ["warp", "warpterminal"] },
  { "company": "Zed Industries",     "tokens": ["zed", "zedindustries"] },
  { "company": "Raycast",            "tokens": ["raycast"] },
  { "company": "Livekit",            "tokens": ["livekit"] },
  { "company": "Ably",               "tokens": ["ably"] },
  { "company": "Pusher",             "tokens": ["pusher"] },
  { "company": "Kong",               "tokens": ["kong", "konghq"] },
  { "company": "Plane",              "tokens": ["plane", "makeplane"] },
  { "company": "Formbricks",         "tokens": ["formbricks"] },
  { "company": "Chatwoot",           "tokens": ["chatwoot"] },
  { "company": "Zepto",              "tokens": ["zepto", "kiranakart"] },
  { "company": "BharatPe",           "tokens": ["bharatpe"] },
  { "company": "Khatabook",          "tokens": ["khatabook"] },
  { "company": "Zetwerk",            "tokens": ["zetwerk"] },
  { "company": "MoEngage",           "tokens": ["moengage"] },
  { "company": "CleverTap",          "tokens": ["clevertap"] },
  { "company": "WebEngage",          "tokens": ["webengage"] },
  { "company": "Yellow.ai",          "tokens": ["yellowai", "yellow-ai", "yellowmessenger"] },
  { "company": "Observe.AI",         "tokens": ["observe-ai", "observeai"] },
  { "company": "Exotel",             "tokens": ["exotel"] },
  { "company": "Sprinklr",           "tokens": ["sprinklr"] },
  { "company": "Icertis",            "tokens": ["icertis"] },
  { "company": "Innovaccer",         "tokens": ["innovaccer"] },
  { "company": "LeadSquared",        "tokens": ["leadsquared"] },
  { "company": "Perfios",            "tokens": ["perfios"] },
  { "company": "M2P Fintech",        "tokens": ["m2pfintech", "m2p"] },
  { "company": "Cashfree",           "tokens": ["cashfree", "cashfreepayments"] },
  { "company": "Hasura",             "tokens": ["hasura"] },
  { "company": "Smallcase",          "tokens": ["smallcase"] },
  { "company": "Upstox",             "tokens": ["upstox"] },
  { "company": "Jupiter Money",      "tokens": ["jupitermoney", "jupiter"] },
  { "company": "Fi Money",           "tokens": ["fi", "epifi"] },
  { "company": "Recko",              "tokens": ["recko"] },
  { "company": "Hyperface",          "tokens": ["hyperface"] },
  { "company": "Niyo",               "tokens": ["niyo", "niyosolutions"] },
  { "company": "OkCredit",           "tokens": ["okcredit"] },
  { "company": "Simpl",              "tokens": ["simpl", "getbux"] },
  { "company": "EarlySalary",        "tokens": ["earlysalary"] },
  { "company": "Kreditbee",          "tokens": ["kreditbee"] },
  { "company": "Credgenics",         "tokens": ["credgenics"] },
  { "company": "Ola",                "tokens": ["ola", "olamobility", "ani-technologies"] },
  { "company": "Rapido",             "tokens": ["rapido"] },
  { "company": "Porter",             "tokens": ["porter", "porter-logistics"] },
  { "company": "Navi",               "tokens": ["navi", "navitechnologies"] },
  { "company": "MediBuddy",          "tokens": ["medibuddy"] },
  { "company": "Pristyn Care",       "tokens": ["pristyncare"] },
  { "company": "Practo",             "tokens": ["practo"] },
  { "company": "Cure.fit",           "tokens": ["curefit"] },
  { "company": "Vedantu",            "tokens": ["vedantu"] },
  { "company": "Unacademy",          "tokens": ["unacademy"] },
  { "company": "LEAD School",        "tokens": ["leadschool", "lead"] },
  { "company": "Classplus",          "tokens": ["classplus"] },
  { "company": "Scaler",             "tokens": ["scaler", "scaleracademy", "interviewbit"] },
  { "company": "Apna",               "tokens": ["apna", "apnatime"] },
  { "company": "Springworks",        "tokens": ["springworks"] },
  { "company": "Keka",               "tokens": ["keka"] },
  { "company": "Capillary Tech",     "tokens": ["capillary", "capillarytechnologies"] },
  { "company": "Persistent Systems", "tokens": ["persistent", "persistentsystems"] },
  { "company": "Happiest Minds",     "tokens": ["happiestminds"] },
  { "company": "Mphasis",            "tokens": ["mphasis"] },
  { "company": "Hexaware",           "tokens": ["hexaware"] },
  { "company": "New Relic",          "tokens": ["NewRelic", "new-relic", "newrelic"] },
  { "company": "Rapid7",             "tokens": ["Rapid7", "rapid7"] },
  { "company": "Tenable",            "tokens": ["Tenable", "tenable"] },
  { "company": "EPAM",               "tokens": ["EPAM", "epam"] },
  { "company": "Appian",             "tokens": ["Appian", "appian"] },
  { "company": "Infobip",            "tokens": ["Infobip", "infobip"] },
  { "company": "Cvent",              "tokens": ["Cvent", "cvent"] },
  { "company": "Palo Alto Networks", "tokens": ["paloaltonetworks"] },
  { "company": "Fortinet",           "tokens": ["fortinet"] },
  { "company": "Splunk",             "tokens": ["splunk"] },
  { "company": "Intuit",             "tokens": ["intuit"] },
  { "company": "Autodesk",           "tokens": ["autodesk"] },
  { "company": "NetApp",             "tokens": ["netapp"] },
  { "company": "Juniper Networks",   "tokens": ["juniper", "junipernetworks"] },
  { "company": "Akamai",             "tokens": ["akamai"] },
  { "company": "F5",                 "tokens": ["f5", "f5networks"] },
  { "company": "Veeva Systems",      "tokens": ["veeva"] },
  { "company": "Trimble",            "tokens": ["trimble"] },
  { "company": "Zebra Technologies", "tokens": ["zebra", "zebratechnologies"] },
  { "company": "Western Digital",    "tokens": ["westerndigital"] },
  { "company": "Seagate",            "tokens": ["seagate"] },
  { "company": "AMD",                "tokens": ["amd"] },
  { "company": "Marvell",            "tokens": ["marvell"] },
  { "company": "Broadcom",           "tokens": ["broadcom"] },
  { "company": "Arm",                "tokens": ["arm", "armltd"] },
  { "company": "VMware",             "tokens": ["vmware"] },
  { "company": "Dell",               "tokens": ["dell"] },
  { "company": "Lam Research",       "tokens": ["lamresearch"] },
  { "company": "Goldman Sachs",      "tokens": ["goldmansachs"] },
  { "company": "Morgan Stanley",     "tokens": ["morganstanley"] },
  { "company": "Zensar",             "tokens": ["zensar"] },
  { "company": "Cyient",             "tokens": ["cyient"] },
  { "company": "L&T Technology",     "tokens": ["ltts"] }
]
